YOESorter2/YOESorter2.srcs/sources_1/new/3.v
`timescale 1ns/1ps
module Datapath(
    input             clk,
    input             reset,
    input             start,
    output reg        done,

    // New individual memory outputs
    output       [15:0] mem_outx0,
    output       [15:0] mem_outx1,
    output       [15:0] mem_outx2,
    output       [15:0] mem_outx3,
    output       [15:0] mem_outx4,
    output       [15:0] mem_outx5,
    output       [15:0] mem_outx6,
    output       [15:0] mem_outx7
);
    // Internal memory array (8 words of 16 bits)
    reg [15:0] mem [0:7];

    // Indices for bubble sort
    reg [2:0] i, j;
    reg [15:0] temp;
    reg        working;

    // Initialize memory with unsorted values
    initial begin
        mem[0] = 16'd50;
        mem[1] = 16'd20;
        mem[2] = 16'd30;
        mem[3] = 16'd70;
        mem[4] = 16'd10;
        mem[5] = 16'd90;
        mem[6] = 16'd40;
        mem[7] = 16'd60;
    end

    // Latch the start signal into 'working'
    always @(posedge clk or posedge reset) begin
        if (reset) 
            working <= 1'b0;
        else if (start) 
            working <= 1'b1;
    end

    // Bubble-sort logic
    always @(posedge clk or posedge reset) begin
        if (reset) begin
            i    <= 3'd0;
            j    <= 3'd0;
            done <= 1'b0;
        end else if (working && !done) begin
            if (mem[j] > mem[j+1]) begin
                temp      = mem[j];
                mem[j]    = mem[j+1];
                mem[j+1]  = temp;
            end
            if (j < 6 - i) begin
                j <= j + 1;
            end else begin
                j <= 3'd0;
                if (i < 6) begin
                    i <= i + 1;
                end else begin
                    done <= 1'b1;
                end
            end
        end
    end

    // Expose each internal mem[k] as a separate output
    assign mem_outx0 = mem[0];
    assign mem_outx1 = mem[1];
    assign mem_outx2 = mem[2];
    assign mem_outx3 = mem[3];
    assign mem_outx4 = mem[4];
    assign mem_outx5 = mem[5];
    assign mem_outx6 = mem[6];
    assign mem_outx7 = mem[7];
endmodule

YOESorter2/YOESorter2.srcs/sources_1/new/2.v
`timescale 1ns/1ps
module Top(
    input             clk,
    input             reset,
    input             start,
    output            done,

    // Pass-through of the eight memory outputs
    output      [15:0] mem_outx0,
    output      [15:0] mem_outx1,
    output      [15:0] mem_outx2,
    output      [15:0] mem_outx3,
    output      [15:0] mem_outx4,
    output      [15:0] mem_outx5,
    output      [15:0] mem_outx6,
    output      [15:0] mem_outx7
);
    Datapath dp (
        .clk      (clk),
        .reset    (reset),
        .start    (start),
        .done     (done),

        .mem_outx0(mem_outx0),
        .mem_outx1(mem_outx1),
        .mem_outx2(mem_outx2),
        .mem_outx3(mem_outx3),
        .mem_outx4(mem_outx4),
        .mem_outx5(mem_outx5),
        .mem_outx6(mem_outx6),
        .mem_outx7(mem_outx7)
    );
endmodule

YOESorter2/YOESorter2.srcs/sim_1/new/testbench.v
`timescale 1ns/1ps
module testbench;
    reg        clk;
    reg        reset;
    reg        start;
    wire       done;

    // Wires to capture each mem_outxN
    wire [15:0] mem_outx0;
    wire [15:0] mem_outx1;
    wire [15:0] mem_outx2;
    wire [15:0] mem_outx3;
    wire [15:0] mem_outx4;
    wire [15:0] mem_outx5;
    wire [15:0] mem_outx6;
    wire [15:0] mem_outx7;

    // Instantiate Top
    Top uut (
        .clk      (clk),
        .reset    (reset),
        .start    (start),
        .done     (done),
        .mem_outx0(mem_outx0),
        .mem_outx1(mem_outx1),
        .mem_outx2(mem_outx2),
        .mem_outx3(mem_outx3),
        .mem_outx4(mem_outx4),
        .mem_outx5(mem_outx5),
        .mem_outx6(mem_outx6),
        .mem_outx7(mem_outx7)
    );

    // 10 ns clock
    initial clk = 0;
    always #1 clk = ~clk;

    integer i;

    initial begin
        // Dump everything
        $dumpfile("sorting.vcd");
        $dumpvars(0, testbench, uut);

        // Reset and initial conditions
        reset = 1;
        start = 0;
        #20;
        reset = 0;
        #10;

        // Print unsorted memory
        $display("\n--- Memory before sorting ---");
        $display(" mem[0] = %0d", mem_outx0);
        $display(" mem[1] = %0d", mem_outx1);
        $display(" mem[2] = %0d", mem_outx2);
        $display(" mem[3] = %0d", mem_outx3);
        $display(" mem[4] = %0d", mem_outx4);
        $display(" mem[5] = %0d", mem_outx5);
        $display(" mem[6] = %0d", mem_outx6);
        $display(" mem[7] = %0d", mem_outx7);

        // Pulse start to kick off sorting
        #10;
        start = 1;
        #10;
        start = 0;

        // Wait for done
        @(posedge done);
        #5;

        // Print sorted memory
        $display("\n--- Memory after sorting ---");
        $display(" mem[0] = %0d", mem_outx0);
        $display(" mem[1] = %0d", mem_outx1);
        $display(" mem[2] = %0d", mem_outx2);
        $display(" mem[3] = %0d", mem_outx3);
        $display(" mem[4] = %0d", mem_outx4);
        $display(" mem[5] = %0d", mem_outx5);
        $display(" mem[6] = %0d", mem_outx6);
        $display(" mem[7] = %0d", mem_outx7);

        $display("\nSorting done at time %0t ns\n", $time);
        $finish;
    end
endmodule

YOESorter2/YOESorter2.sim/sim_1/behav/xsim/sorting.vcd
$date
   Wed Apr 30 17:42:34 2025
$end
$version
  2019.1
$end
$timescale
  1ps
$end
$scope module testbench $end
$var reg 1 ! clk $end
$var reg 1 " reset $end
$var reg 1 # start $end
$var wire 1 $ done $end
$var wire 16 % mem_outx0 [15:0] $end
$var wire 16 & mem_outx1 [15:0] $end
$var wire 16 ' mem_outx2 [15:0] $end
$var wire 16 ( mem_outx3 [15:0] $end
$var wire 16 ) mem_outx4 [15:0] $end
$var wire 16 * mem_outx5 [15:0] $end
$var wire 16 + mem_outx6 [15:0] $end
$var wire 16 , mem_outx7 [15:0] $end
$var integer 32 - i $end
$scope module uut $end
$var wire 1 . clk $end
$var wire 1 / reset $end
$var wire 1 0 start $end
$var wire 1 $ done $end
$var wire 16 % mem_outx0 [15:0] $end
$var wire 16 & mem_outx1 [15:0] $end
$var wire 16 ' mem_outx2 [15:0] $end
$var wire 16 ( mem_outx3 [15:0] $end
$var wire 16 ) mem_outx4 [15:0] $end
$var wire 16 * mem_outx5 [15:0] $end
$var wire 16 + mem_outx6 [15:0] $end
$var wire 16 , mem_outx7 [15:0] $end
$scope module dp $end
$var wire 1 . clk $end
$var wire 1 / reset $end
$var wire 1 0 start $end
$var reg 1 1 done $end
$var wire 16 % mem_outx0 [15:0] $end
$var wire 16 & mem_outx1 [15:0] $end
$var wire 16 ' mem_outx2 [15:0] $end
$var wire 16 ( mem_outx3 [15:0] $end
$var wire 16 ) mem_outx4 [15:0] $end
$var wire 16 * mem_outx5 [15:0] $end
$var wire 16 + mem_outx6 [15:0] $end
$var wire 16 , mem_outx7 [15:0] $end
$var reg 3 2 i [2:0] $end
$var reg 3 3 j [2:0] $end
$var reg 16 4 temp [15:0] $end
$var reg 1 5 working $end
$upscope $end
$upscope $end
$upscope $end
$enddefinitions $end
#0
$dumpvars
0!
1"
0#
0$
b110010 %
b10100 &
b11110 '
b1000110 (
b1010 )
b1011010 *
b101000 +
b111100 ,
bx -
0.
1/
00
01
b0 2
b0 3
bx 4
05
$end
#1000
1!
1.
#2000
0!
0.
#3000
1!
1.
#4000
0!
0.
#5000
1!
1.
#6000
0!
0.
#7000
1!
1.
#8000
0!
0.
#9000
1!
1.
#10000
0!
0.
#11000
1!
1.
#12000
0!
0.
#13000
1!
1.
#14000
0!
0.
#15000
1!
1.
#16000
0!
0.
#17000
1!
1.
#18000
0!
0.
#19000
1!
1.
#20000
0!
0"
0.
0/
#21000
1!
1.
#22000
0!
0.
#23000
1!
1.
#24000
0!
0.
#25000
1!
1.
#26000
0!
0.
#27000
1!
1.
#28000
0!
0.
#29000
1!
1.
#30000
0!
0.
#31000
1!
1.
#32000
0!
0.
#33000
1!
1.
#34000
0!
0.
#35000
1!
1.
#36000
0!
0.
#37000
1!
1.
#38000
0!
0.
#39000
1!
1.
#40000
0!
1#
0.
10
#41000
1!
1.
15
#42000
0!
0.
#43000
1!
b10100 %
b110010 &
1.
b1 3
b110010 4
#44000
0!
0.
#45000
1!
b11110 &
b110010 '
1.
b10 3
#46000
0!
0.
#47000
1!
1.
b11 3
#48000
0!
0.
#49000
1!
b1010 (
b1000110 )
1.
b100 3
b1000110 4
#50000
0!
0#
0.
00
#51000
1!
1.
b101 3
#52000
0!
0.
#53000
1!
b101000 *
b1011010 +
1.
b110 3
b1011010 4
#54000
0!
0.
#55000
1!
b111100 +
b1011010 ,
1.
b1 2
b0 3
#56000
0!
0.
#57000
1!
1.
b1 3
#58000
0!
0.
#59000
1!
1.
b10 3
#60000
0!
0.
#61000
1!
b1010 '
b110010 (
1.
b11 3
b110010 4
#62000
0!
0.
#63000
1!
1.
b100 3
#64000
0!
0.
#65000
1!
b101000 )
b1000110 *
1.
b101 3
b1000110 4
#66000
0!
0.
#67000
1!
b111100 *
b1000110 +
1.
b10 2
b0 3
#68000
0!
0.
#69000
1!
1.
b1 3
#70000
0!
0.
#71000
1!
b1010 &
b11110 '
1.
b10 3
b11110 4
#72000
0!
0.
#73000
1!
1.
b11 3
#74000
0!
0.
#75000
1!
b101000 (
b110010 )
1.
b100 3
b110010 4
#76000
0!
0.
#77000
1!
1.
b11 2
b0 3
#78000
0!
0.
#79000
1!
b1010 %
b10100 &
1.
b1 3
b10100 4
#80000
0!
0.
#81000
1!
1.
b10 3
#82000
0!
0.
#83000
1!
1.
b11 3
#84000
0!
0.
#85000
1!
1.
b100 2
b0 3
#86000
0!
0.
#87000
1!
1.
b1 3
#88000
0!
0.
#89000
1!
1.
b10 3
#90000
0!
0.
#91000
1!
1.
b101 2
b0 3
#92000
0!
0.
#93000
1!
1.
b1 3
#94000
0!
0.
#95000
1!
1.
b110 2
b0 3
#96000
0!
0.
#97000
1!
1$
1.
11
